LICENSE
README.txt
TODO.txt
ez_setup.py
setup.py
misc/davlib.py
misc/getowner.py
misc/synch.py
tests/__init__.py
tests/test_acl.py
tests/test_http.py
tests/test_ticket.py
tests/test_util.py
tests/test_webdav.py
zanshin/__init__.py
zanshin/acl.py
zanshin/error.py
zanshin/http.py
zanshin/ticket.py
zanshin/util.py
zanshin/webdav.py
zanshin/webdav_server.py
zanshin.egg-info/PKG-INFO
zanshin.egg-info/SOURCES.txt
zanshin.egg-info/dependency_links.txt
zanshin.egg-info/top_level.txt
zanshin.egg-info/zip-safe