Metadata-Version: 1.0
Name: zanshin
Version: 0.6
Summary: High-level library for HTTP, WebDAV and CalDAV operations
Home-page: http://chandlerproject.org/Projects/ZanshinProject
Author: Grant Baillie
Author-email: grant@osafoundation.org
License: UNKNOWN
Platform: UNKNOWN
Classifier: Development Status :: 3 - Alpha
Classifier: Environment :: Console
Classifier: Framework :: Chandler
Classifier: Intended Audience :: Developers
Classifier: License :: OSI Approved :: MIT License
Classifier: Operating System :: OS Independent
Classifier: Programming Language :: Python
Classifier: Topic :: Software Development :: Libraries :: Python Modules
